convopilot/__init__.py
convopilot/file_writer.py
convopilot/google_doc.py
convopilot/gpt_api.py
convopilot/interface.py
convopilot/llm_insight_generator.py
convopilot/llm_models.py
convopilot/module_factory.py
convopilot/pipeline.py
convopilot/pyaudio_recorder.py
convopilot/record_audio.py
convopilot/server.py
convopilot/whisper_transcriber.py
convopilot/bin/ffmpeg
convopilot/bin/portaudio/lib/libportaudio.2.dylib
convopilot/bin/portaudio/lib/libportaudio.a
convopilot/bin/portaudio/lib/libportaudio.dylib
convopilot/bin/portaudio/lib/libportaudiocpp.0.dylib
convopilot/bin/portaudio/lib/libportaudiocpp.a
convopilot/bin/portaudio/lib/libportaudiocpp.dylib
convopilot/bin/portaudio/lib/pkgconfig/portaudio-2.0.pc
convopilot/bin/portaudio/lib/pkgconfig/portaudiocpp.pc
convopilot-0.2.8.dist-info/LICENSE
convopilot-0.2.8.dist-info/METADATA
convopilot-0.2.8.dist-info/WHEEL
convopilot-0.2.8.dist-info/entry_points.txt
convopilot-0.2.8.dist-info/top_level.txt
convopilot-0.2.8.dist-info/RECORD
