Metadata-Version: 2.1
Name: convopilot
Version: 0.2.8
Summary: An AI tool to help users better navigate conversations.
Home-page: https://github.com/zhang123cnn/convopilot
Author: Xiaomeng Zhang
Author-email: zhang123cnn@gmail.com
License: MIT
License-File: LICENSE
Requires-Dist: aiohttp (==3.8.5)
Requires-Dist: aiosignal (==1.3.1)
Requires-Dist: altgraph (==0.17.4)
Requires-Dist: async-timeout (==4.0.2)
Requires-Dist: attrs (==23.1.0)
Requires-Dist: bidict (==0.22.1)
Requires-Dist: bleach (==6.0.0)
Requires-Dist: blinker (==1.6.2)
Requires-Dist: cachetools (==5.3.1)
Requires-Dist: certifi (==2023.7.22)
Requires-Dist: charset-normalizer (==3.2.0)
Requires-Dist: click (==8.1.7)
Requires-Dist: docutils (==0.20.1)
Requires-Dist: ffmpeg-python (==0.2.0)
Requires-Dist: filelock (==3.12.2)
Requires-Dist: Flask (==2.3.3)
Requires-Dist: Flask-Cors (==4.0.0)
Requires-Dist: Flask-SocketIO (==5.3.5)
Requires-Dist: frozenlist (==1.4.0)
Requires-Dist: future (==0.18.3)
Requires-Dist: google-api-core (==2.11.1)
Requires-Dist: google-api-python-client (==2.96.0)
Requires-Dist: google-auth (==2.22.0)
Requires-Dist: google-auth-httplib2 (==0.1.0)
Requires-Dist: google-auth-oauthlib (==1.0.0)
Requires-Dist: googleapis-common-protos (==1.60.0)
Requires-Dist: httplib2 (==0.22.0)
Requires-Dist: idna (==3.4)
Requires-Dist: importlib-metadata (==6.8.0)
Requires-Dist: itsdangerous (==2.1.2)
Requires-Dist: jaraco.classes (==3.3.0)
Requires-Dist: Jinja2 (==3.1.2)
Requires-Dist: keyring (==24.2.0)
Requires-Dist: llvmlite (==0.40.1)
Requires-Dist: macholib (==1.16.3)
Requires-Dist: markdown-it-py (==3.0.0)
Requires-Dist: MarkupSafe (==2.1.3)
Requires-Dist: mdurl (==0.1.2)
Requires-Dist: more-itertools (==10.1.0)
Requires-Dist: mpmath (==1.3.0)
Requires-Dist: multidict (==6.0.4)
Requires-Dist: networkx (==3.1)
Requires-Dist: numba (==0.57.1)
Requires-Dist: numpy (==1.24.4)
Requires-Dist: oauthlib (==3.2.2)
Requires-Dist: openai (==0.27.8)
Requires-Dist: openai-whisper (==20230314)
Requires-Dist: packaging (==23.1)
Requires-Dist: pkginfo (==1.9.6)
Requires-Dist: protobuf (==4.24.0)
Requires-Dist: pyasn1 (==0.5.0)
Requires-Dist: pyasn1-modules (==0.3.0)
Requires-Dist: PyAudio (==0.2.13)
Requires-Dist: Pygments (==2.16.1)
Requires-Dist: pyinstaller (==6.0.0)
Requires-Dist: pyinstaller-hooks-contrib (==2023.9)
Requires-Dist: pyparsing (==3.1.1)
Requires-Dist: Pypubsub (==4.0.3)
Requires-Dist: python-dotenv (==1.0.0)
Requires-Dist: python-engineio (==4.6.1)
Requires-Dist: python-socketio (==5.8.0)
Requires-Dist: readme-renderer (==40.0)
Requires-Dist: regex (==2023.6.3)
Requires-Dist: requests (==2.31.0)
Requires-Dist: requests-oauthlib (==1.3.1)
Requires-Dist: requests-toolbelt (==1.0.0)
Requires-Dist: rfc3986 (==2.0.0)
Requires-Dist: rich (==13.5.2)
Requires-Dist: rsa (==4.9)
Requires-Dist: six (==1.16.0)
Requires-Dist: sympy (==1.12)
Requires-Dist: tiktoken (==0.3.1)
Requires-Dist: torch (==2.0.1)
Requires-Dist: tqdm (==4.65.0)
Requires-Dist: twine (==4.0.2)
Requires-Dist: typing-extensions (==4.7.1)
Requires-Dist: uritemplate (==4.1.1)
Requires-Dist: urllib3 (==1.26.16)
Requires-Dist: webencodings (==0.5.1)
Requires-Dist: Werkzeug (==2.3.7)
Requires-Dist: yarl (==1.9.2)
Requires-Dist: zipp (==3.16.2)
